{
  "_meta": {
    "version": 12,
    "info": {
      "name": "Piles",
      "image": "/assets/245080149_4003",
      "rules": "",
      "bgg": "",
      "year": "2021",
      "mode": "Tutorial",
      "time": "",
      "attribution": "The rank icon images are by user Ingegneus and are released into the Public Domain through CC0.",
      "showName": false,
      "lastUpdate": 1677662750421,
      "skill": "",
      "description": "",
      "similarImage": "",
      "similarName": "",
      "similarAwards": "",
      "ruleText": "",
      "helpText": "",
      "variantImage": "",
      "variant": "Advanced",
      "language": "en-US",
      "players": "1"
    }
  },
  "oit_2_C": {
    "type": "card",
    "id": "oit_2_C",
    "parent": "oitfP",
    "deck": "example1D",
    "cardType": "C 02"
  },
  "8fr3": {
    "id": "8fr3",
    "x": 560,
    "width": 430,
    "height": 60,
    "z": 74,
    "css": "font-size: 60px",
    "text": "Piles: Advanced",
    "y": -2,
    "movable": false,
    "movableInEdit": false
  },
  "yxq7": {
    "type": "holder",
    "id": "yxq7",
    "x": 409.75,
    "y": 769,
    "dropTarget": {
      "type": "card"
    },
    "z": 48
  },
  "yxq7B": {
    "id": "yxq7B",
    "parent": "yxq7",
    "fixedParent": true,
    "y": 171.36,
    "width": 111,
    "height": 40,
    "type": "button",
    "text": "Recall & Shuffle",
    "movableInEdit": false,
    "clickRoutine": [
      {
        "func": "RECALL",
        "holder": "${PROPERTY parent}"
      },
      {
        "func": "FLIP",
        "holder": "${PROPERTY parent}",
        "face": 0
      },
      {
        "func": "SHUFFLE",
        "holder": "${PROPERTY parent}"
      }
    ]
  },
  "yxq7D": {
    "type": "deck",
    "id": "yxq7D",
    "parent": "yxq7",
    "x": 12,
    "y": 41,
    "cardTypes": {
      "T 1J": {
        "image": "/i/cards-default/1J.svg",
        "suit": "T",
        "suitColor": "🃏",
        "suitAlt": "5J",
        "rank": "J1",
        "rankA": "J1",
        "rankFixed": "J1 T"
      },
      "T 2J": {
        "image": "/i/cards-default/2J.svg",
        "suit": "T",
        "suitColor": "🃏",
        "suitAlt": "5J",
        "rank": "J2",
        "rankA": "J2",
        "rankFixed": "J2 T"
      },
      "C 01": {
        "image": "/i/cards-default/AC.svg",
        "suit": "C",
        "suitColor": "♣",
        "suitAlt": "1♣",
        "rank": "01",
        "rankA": "5A",
        "rankFixed": "01 C"
      },
      "C 02": {
        "image": "/i/cards-default/2C.svg",
        "suit": "C",
        "suitColor": "♣",
        "suitAlt": "1♣",
        "rank": "02",
        "rankA": "02",
        "rankFixed": "02 C"
      },
      "C 03": {
        "image": "/i/cards-default/3C.svg",
        "suit": "C",
        "suitColor": "♣",
        "suitAlt": "1♣",
        "rank": "03",
        "rankA": "03",
        "rankFixed": "03 C"
      },
      "C 04": {
        "image": "/i/cards-default/4C.svg",
        "suit": "C",
        "suitColor": "♣",
        "suitAlt": "1♣",
        "rank": "04",
        "rankA": "04",
        "rankFixed": "04 C"
      },
      "C 05": {
        "image": "/i/cards-default/5C.svg",
        "suit": "C",
        "suitColor": "♣",
        "suitAlt": "1♣",
        "rank": "05",
        "rankA": "05",
        "rankFixed": "05 C"
      },
      "C 06": {
        "image": "/i/cards-default/6C.svg",
        "suit": "C",
        "suitColor": "♣",
        "suitAlt": "1♣",
        "rank": "06",
        "rankA": "06",
        "rankFixed": "06 C"
      },
      "C 07": {
        "image": "/i/cards-default/7C.svg",
        "suit": "C",
        "suitColor": "♣",
        "suitAlt": "1♣",
        "rank": "07",
        "rankA": "07",
        "rankFixed": "07 C"
      },
      "C 08": {
        "image": "/i/cards-default/8C.svg",
        "suit": "C",
        "suitColor": "♣",
        "suitAlt": "1♣",
        "rank": "08",
        "rankA": "08",
        "rankFixed": "08 C"
      },
      "C 09": {
        "image": "/i/cards-default/9C.svg",
        "suit": "C",
        "suitColor": "♣",
        "suitAlt": "1♣",
        "rank": "09",
        "rankA": "09",
        "rankFixed": "09 C"
      },
      "C 10": {
        "image": "/i/cards-default/TC.svg",
        "suit": "C",
        "suitColor": "♣",
        "suitAlt": "1♣",
        "rank": "10",
        "rankA": "10",
        "rankFixed": "10 C"
      },
      "C 2J": {
        "image": "/i/cards-default/JC.svg",
        "suit": "C",
        "suitColor": "♣",
        "suitAlt": "1♣",
        "rank": "2J",
        "rankA": "2J",
        "rankFixed": "2J C"
      },
      "C 3Q": {
        "image": "/i/cards-default/QC.svg",
        "suit": "C",
        "suitColor": "♣",
        "suitAlt": "1♣",
        "rank": "3Q",
        "rankA": "3Q",
        "rankFixed": "3Q C"
      },
      "C 4K": {
        "image": "/i/cards-default/KC.svg",
        "suit": "C",
        "suitColor": "♣",
        "suitAlt": "1♣",
        "rank": "4K",
        "rankA": "4K",
        "rankFixed": "4K C"
      },
      "D 01": {
        "image": "/i/cards-default/AD.svg",
        "suit": "D",
        "suitColor": "♦",
        "suitAlt": "4♦",
        "rank": "01",
        "rankA": "5A",
        "rankFixed": "01 D"
      },
      "D 02": {
        "image": "/i/cards-default/2D.svg",
        "suit": "D",
        "suitColor": "♦",
        "suitAlt": "4♦",
        "rank": "02",
        "rankA": "02",
        "rankFixed": "02 D"
      },
      "D 03": {
        "image": "/i/cards-default/3D.svg",
        "suit": "D",
        "suitColor": "♦",
        "suitAlt": "4♦",
        "rank": "03",
        "rankA": "03",
        "rankFixed": "03 D"
      },
      "D 04": {
        "image": "/i/cards-default/4D.svg",
        "suit": "D",
        "suitColor": "♦",
        "suitAlt": "4♦",
        "rank": "04",
        "rankA": "04",
        "rankFixed": "04 D"
      },
      "D 05": {
        "image": "/i/cards-default/5D.svg",
        "suit": "D",
        "suitColor": "♦",
        "suitAlt": "4♦",
        "rank": "05",
        "rankA": "05",
        "rankFixed": "05 D"
      },
      "D 06": {
        "image": "/i/cards-default/6D.svg",
        "suit": "D",
        "suitColor": "♦",
        "suitAlt": "4♦",
        "rank": "06",
        "rankA": "06",
        "rankFixed": "06 D"
      },
      "D 07": {
        "image": "/i/cards-default/7D.svg",
        "suit": "D",
        "suitColor": "♦",
        "suitAlt": "4♦",
        "rank": "07",
        "rankA": "07",
        "rankFixed": "07 D"
      },
      "D 08": {
        "image": "/i/cards-default/8D.svg",
        "suit": "D",
        "suitColor": "♦",
        "suitAlt": "4♦",
        "rank": "08",
        "rankA": "08",
        "rankFixed": "08 D"
      },
      "D 09": {
        "image": "/i/cards-default/9D.svg",
        "suit": "D",
        "suitColor": "♦",
        "suitAlt": "4♦",
        "rank": "09",
        "rankA": "09",
        "rankFixed": "09 D"
      },
      "D 10": {
        "image": "/i/cards-default/TD.svg",
        "suit": "D",
        "suitColor": "♦",
        "suitAlt": "4♦",
        "rank": "10",
        "rankA": "10",
        "rankFixed": "10 D"
      },
      "D 2J": {
        "image": "/i/cards-default/JD.svg",
        "suit": "D",
        "suitColor": "♦",
        "suitAlt": "4♦",
        "rank": "2J",
        "rankA": "2J",
        "rankFixed": "2J D"
      },
      "D 3Q": {
        "image": "/i/cards-default/QD.svg",
        "suit": "D",
        "suitColor": "♦",
        "suitAlt": "4♦",
        "rank": "3Q",
        "rankA": "3Q",
        "rankFixed": "3Q D"
      },
      "D 4K": {
        "image": "/i/cards-default/KD.svg",
        "suit": "D",
        "suitColor": "♦",
        "suitAlt": "4♦",
        "rank": "4K",
        "rankA": "4K",
        "rankFixed": "4K D"
      },
      "H 01": {
        "image": "/i/cards-default/AH.svg",
        "suit": "H",
        "suitColor": "♥",
        "suitAlt": "2♥",
        "rank": "01",
        "rankA": "5A",
        "rankFixed": "01 H"
      },
      "H 02": {
        "image": "/i/cards-default/2H.svg",
        "suit": "H",
        "suitColor": "♥",
        "suitAlt": "2♥",
        "rank": "02",
        "rankA": "02",
        "rankFixed": "02 H"
      },
      "H 03": {
        "image": "/i/cards-default/3H.svg",
        "suit": "H",
        "suitColor": "♥",
        "suitAlt": "2♥",
        "rank": "03",
        "rankA": "03",
        "rankFixed": "03 H"
      },
      "H 04": {
        "image": "/i/cards-default/4H.svg",
        "suit": "H",
        "suitColor": "♥",
        "suitAlt": "2♥",
        "rank": "04",
        "rankA": "04",
        "rankFixed": "04 H"
      },
      "H 05": {
        "image": "/i/cards-default/5H.svg",
        "suit": "H",
        "suitColor": "♥",
        "suitAlt": "2♥",
        "rank": "05",
        "rankA": "05",
        "rankFixed": "05 H"
      },
      "H 06": {
        "image": "/i/cards-default/6H.svg",
        "suit": "H",
        "suitColor": "♥",
        "suitAlt": "2♥",
        "rank": "06",
        "rankA": "06",
        "rankFixed": "06 H"
      },
      "H 07": {
        "image": "/i/cards-default/7H.svg",
        "suit": "H",
        "suitColor": "♥",
        "suitAlt": "2♥",
        "rank": "07",
        "rankA": "07",
        "rankFixed": "07 H"
      },
      "H 08": {
        "image": "/i/cards-default/8H.svg",
        "suit": "H",
        "suitColor": "♥",
        "suitAlt": "2♥",
        "rank": "08",
        "rankA": "08",
        "rankFixed": "08 H"
      },
      "H 09": {
        "image": "/i/cards-default/9H.svg",
        "suit": "H",
        "suitColor": "♥",
        "suitAlt": "2♥",
        "rank": "09",
        "rankA": "09",
        "rankFixed": "09 H"
      },
      "H 10": {
        "image": "/i/cards-default/TH.svg",
        "suit": "H",
        "suitColor": "♥",
        "suitAlt": "2♥",
        "rank": "10",
        "rankA": "10",
        "rankFixed": "10 H"
      },
      "H 2J": {
        "image": "/i/cards-default/JH.svg",
        "suit": "H",
        "suitColor": "♥",
        "suitAlt": "2♥",
        "rank": "2J",
        "rankA": "2J",
        "rankFixed": "2J H"
      },
      "H 3Q": {
        "image": "/i/cards-default/QH.svg",
        "suit": "H",
        "suitColor": "♥",
        "suitAlt": "2♥",
        "rank": "3Q",
        "rankA": "3Q",
        "rankFixed": "3Q H"
      },
      "H 4K": {
        "image": "/i/cards-default/KH.svg",
        "suit": "H",
        "suitColor": "♥",
        "suitAlt": "2♥",
        "rank": "4K",
        "rankA": "4K",
        "rankFixed": "4K H"
      },
      "S 01": {
        "image": "/i/cards-default/AS.svg",
        "suit": "S",
        "suitColor": "♠",
        "suitAlt": "3♠",
        "rank": "01",
        "rankA": "5A",
        "rankFixed": "01 S"
      },
      "S 02": {
        "image": "/i/cards-default/2S.svg",
        "suit": "S",
        "suitColor": "♠",
        "suitAlt": "3♠",
        "rank": "02",
        "rankA": "02",
        "rankFixed": "02 S"
      },
      "S 03": {
        "image": "/i/cards-default/3S.svg",
        "suit": "S",
        "suitColor": "♠",
        "suitAlt": "3♠",
        "rank": "03",
        "rankA": "03",
        "rankFixed": "03 S"
      },
      "S 04": {
        "image": "/i/cards-default/4S.svg",
        "suit": "S",
        "suitColor": "♠",
        "suitAlt": "3♠",
        "rank": "04",
        "rankA": "04",
        "rankFixed": "04 S"
      },
      "S 05": {
        "image": "/i/cards-default/5S.svg",
        "suit": "S",
        "suitColor": "♠",
        "suitAlt": "3♠",
        "rank": "05",
        "rankA": "05",
        "rankFixed": "05 S"
      },
      "S 06": {
        "image": "/i/cards-default/6S.svg",
        "suit": "S",
        "suitColor": "♠",
        "suitAlt": "3♠",
        "rank": "06",
        "rankA": "06",
        "rankFixed": "06 S"
      },
      "S 07": {
        "image": "/i/cards-default/7S.svg",
        "suit": "S",
        "suitColor": "♠",
        "suitAlt": "3♠",
        "rank": "07",
        "rankA": "07",
        "rankFixed": "07 S"
      },
      "S 08": {
        "image": "/i/cards-default/8S.svg",
        "suit": "S",
        "suitColor": "♠",
        "suitAlt": "3♠",
        "rank": "08",
        "rankA": "08",
        "rankFixed": "08 S"
      },
      "S 09": {
        "image": "/i/cards-default/9S.svg",
        "suit": "S",
        "suitColor": "♠",
        "suitAlt": "3♠",
        "rank": "09",
        "rankA": "09",
        "rankFixed": "09 S"
      },
      "S 10": {
        "image": "/i/cards-default/TS.svg",
        "suit": "S",
        "suitColor": "♠",
        "suitAlt": "3♠",
        "rank": "10",
        "rankA": "10",
        "rankFixed": "10 S"
      },
      "S 2J": {
        "image": "/i/cards-default/JS.svg",
        "suit": "S",
        "suitColor": "♠",
        "suitAlt": "3♠",
        "rank": "2J",
        "rankA": "2J",
        "rankFixed": "2J S"
      },
      "S 3Q": {
        "image": "/i/cards-default/QS.svg",
        "suit": "S",
        "suitColor": "♠",
        "suitAlt": "3♠",
        "rank": "3Q",
        "rankA": "3Q",
        "rankFixed": "3Q S"
      },
      "S 4K": {
        "image": "/i/cards-default/KS.svg",
        "suit": "S",
        "suitColor": "♠",
        "suitAlt": "3♠",
        "rank": "4K",
        "rankA": "4K",
        "rankFixed": "4K S"
      }
    },
    "faceTemplates": [
      {
        "border": false,
        "radius": false,
        "objects": [
          {
            "type": "image",
            "x": 0,
            "y": 0,
            "width": 103,
            "height": 160,
            "value": "/i/cards-default/2B.svg",
            "color": "transparent"
          }
        ]
      },
      {
        "border": false,
        "radius": false,
        "objects": [
          {
            "type": "image",
            "x": 0,
            "y": 0,
            "width": 103,
            "height": 160,
            "color": "transparent",
            "dynamicProperties": {
              "value": "image"
            }
          }
        ]
      }
    ],
    "cardDefaults": {
      "onPileCreation": {
        "handleCSS": "background:blue; color:white",
        "clickRoutine": [
          {
            "func": "CALL",
            "routine": "expandRoutine"
          }
        ],
        "expandRoutine": [
          {
            "func": "SELECT",
            "property": "id",
            "value": "${thisID}"
          },
          {
            "func": "SORT",
            "key": "z"
          },
          {
            "func": "IF",
            "operand1": "${PROPERTY expanded}",
            "operand2": true,
            "relation": "!=",
            "thenRoutine": [
              "var xPos = 0",
              {
                "func": "FOREACH",
                "collection": "DEFAULT",
                "loopRoutine": [
                  {
                    "func": "SET",
                    "collection": [
                      "${widgetID}"
                    ],
                    "property": "x",
                    "value": "${xPos}"
                  },
                  "var xPos = ${xPos} - 35"
                ]
              },
              {
                "func": "SET",
                "property": "expanded",
                "collection": "thisButton",
                "value": true
              }
            ],
            "elseRoutine": [
              "var xPos = 0",
              {
                "func": "FOREACH",
                "collection": "DEFAULT",
                "loopRoutine": [
                  {
                    "func": "SET",
                    "collection": [
                      "${widgetID}"
                    ],
                    "property": "x",
                    "value": "${xPos}"
                  }
                ]
              },
              {
                "func": "SET",
                "property": "expanded",
                "collection": "thisButton",
                "value": false
              }
            ]
          }
        ]
      }
    }
  },
  "yxq7_4_S": {
    "id": "yxq7_4_S",
    "deck": "yxq7D",
    "type": "card",
    "cardType": "S 04",
    "z": 1071,
    "parent": "hzsu"
  },
  "yxq7_5_S": {
    "id": "yxq7_5_S",
    "deck": "yxq7D",
    "type": "card",
    "cardType": "S 05",
    "z": 921,
    "parent": "hzsu"
  },
  "yxq7_6_S": {
    "id": "yxq7_6_S",
    "deck": "yxq7D",
    "type": "card",
    "cardType": "S 06",
    "z": 8076,
    "parent": "hzsu"
  },
  "yxq7_7_S": {
    "id": "yxq7_7_S",
    "deck": "yxq7D",
    "type": "card",
    "cardType": "S 07",
    "z": 1750,
    "parent": "hzsu"
  },
  "yxq7_8_S": {
    "id": "yxq7_8_S",
    "deck": "yxq7D",
    "type": "card",
    "cardType": "S 08",
    "z": 818,
    "parent": "hzsu"
  },
  "yxq7_9_S": {
    "id": "yxq7_9_S",
    "deck": "yxq7D",
    "type": "card",
    "cardType": "S 09",
    "z": 1545,
    "parent": "hzsu"
  },
  "yxq7_T_S": {
    "id": "yxq7_T_S",
    "deck": "yxq7D",
    "type": "card",
    "cardType": "S 10",
    "z": 4996,
    "parent": "hzsu"
  },
  "yxq7_J_S": {
    "id": "yxq7_J_S",
    "deck": "yxq7D",
    "type": "card",
    "cardType": "S 2J",
    "z": 4830,
    "parent": "hzsu"
  },
  "yxq7_Q_S": {
    "id": "yxq7_Q_S",
    "deck": "yxq7D",
    "type": "card",
    "cardType": "S 3Q",
    "z": 9103,
    "parent": "hzsu"
  },
  "yxq7_K_S": {
    "id": "yxq7_K_S",
    "deck": "yxq7D",
    "type": "card",
    "cardType": "S 4K",
    "z": 4397,
    "parent": "hzsu"
  },
  "7i0e": {
    "type": "holder",
    "id": "7i0e",
    "x": 75,
    "y": 769,
    "dropTarget": {
      "type": "card"
    },
    "z": 47
  },
  "7i0eB": {
    "id": "7i0eB",
    "parent": "7i0e",
    "fixedParent": true,
    "y": 171.36,
    "width": 111,
    "height": 40,
    "type": "button",
    "text": "Recall & Shuffle",
    "movableInEdit": false,
    "clickRoutine": [
      {
        "func": "RECALL",
        "holder": "${PROPERTY parent}"
      },
      {
        "func": "FLIP",
        "holder": "${PROPERTY parent}",
        "face": 0
      },
      {
        "func": "SHUFFLE",
        "holder": "${PROPERTY parent}"
      }
    ]
  },
  "7i0eD": {
    "type": "deck",
    "id": "7i0eD",
    "parent": "7i0e",
    "x": 12,
    "y": 41,
    "cardTypes": {
      "T 1J": {
        "image": "/i/cards-default/1J.svg",
        "suit": "T",
        "suitColor": "🃏",
        "suitAlt": "5J",
        "rank": "J1",
        "rankA": "J1",
        "rankFixed": "J1 T"
      },
      "T 2J": {
        "image": "/i/cards-default/2J.svg",
        "suit": "T",
        "suitColor": "🃏",
        "suitAlt": "5J",
        "rank": "J2",
        "rankA": "J2",
        "rankFixed": "J2 T"
      },
      "C 01": {
        "image": "/i/cards-default/AC.svg",
        "suit": "C",
        "suitColor": "♣",
        "suitAlt": "1♣",
        "rank": "01",
        "rankA": "5A",
        "rankFixed": "01 C"
      },
      "C 02": {
        "image": "/i/cards-default/2C.svg",
        "suit": "C",
        "suitColor": "♣",
        "suitAlt": "1♣",
        "rank": "02",
        "rankA": "02",
        "rankFixed": "02 C"
      },
      "C 03": {
        "image": "/i/cards-default/3C.svg",
        "suit": "C",
        "suitColor": "♣",
        "suitAlt": "1♣",
        "rank": "03",
        "rankA": "03",
        "rankFixed": "03 C"
      },
      "C 04": {
        "image": "/i/cards-default/4C.svg",
        "suit": "C",
        "suitColor": "♣",
        "suitAlt": "1♣",
        "rank": "04",
        "rankA": "04",
        "rankFixed": "04 C"
      },
      "C 05": {
        "image": "/i/cards-default/5C.svg",
        "suit": "C",
        "suitColor": "♣",
        "suitAlt": "1♣",
        "rank": "05",
        "rankA": "05",
        "rankFixed": "05 C"
      },
      "C 06": {
        "image": "/i/cards-default/6C.svg",
        "suit": "C",
        "suitColor": "♣",
        "suitAlt": "1♣",
        "rank": "06",
        "rankA": "06",
        "rankFixed": "06 C"
      },
      "C 07": {
        "image": "/i/cards-default/7C.svg",
        "suit": "C",
        "suitColor": "♣",
        "suitAlt": "1♣",
        "rank": "07",
        "rankA": "07",
        "rankFixed": "07 C"
      },
      "C 08": {
        "image": "/i/cards-default/8C.svg",
        "suit": "C",
        "suitColor": "♣",
        "suitAlt": "1♣",
        "rank": "08",
        "rankA": "08",
        "rankFixed": "08 C"
      },
      "C 09": {
        "image": "/i/cards-default/9C.svg",
        "suit": "C",
        "suitColor": "♣",
        "suitAlt": "1♣",
        "rank": "09",
        "rankA": "09",
        "rankFixed": "09 C"
      },
      "C 10": {
        "image": "/i/cards-default/TC.svg",
        "suit": "C",
        "suitColor": "♣",
        "suitAlt": "1♣",
        "rank": "10",
        "rankA": "10",
        "rankFixed": "10 C"
      },
      "C 2J": {
        "image": "/i/cards-default/JC.svg",
        "suit": "C",
        "suitColor": "♣",
        "suitAlt": "1♣",
        "rank": "2J",
        "rankA": "2J",
        "rankFixed": "2J C"
      },
      "C 3Q": {
        "image": "/i/cards-default/QC.svg",
        "suit": "C",
        "suitColor": "♣",
        "suitAlt": "1♣",
        "rank": "3Q",
        "rankA": "3Q",
        "rankFixed": "3Q C"
      },
      "C 4K": {
        "image": "/i/cards-default/KC.svg",
        "suit": "C",
        "suitColor": "♣",
        "suitAlt": "1♣",
        "rank": "4K",
        "rankA": "4K",
        "rankFixed": "4K C"
      },
      "D 01": {
        "image": "/i/cards-default/AD.svg",
        "suit": "D",
        "suitColor": "♦",
        "suitAlt": "4♦",
        "rank": "01",
        "rankA": "5A",
        "rankFixed": "01 D"
      },
      "D 02": {
        "image": "/i/cards-default/2D.svg",
        "suit": "D",
        "suitColor": "♦",
        "suitAlt": "4♦",
        "rank": "02",
        "rankA": "02",
        "rankFixed": "02 D"
      },
      "D 03": {
        "image": "/i/cards-default/3D.svg",
        "suit": "D",
        "suitColor": "♦",
        "suitAlt": "4♦",
        "rank": "03",
        "rankA": "03",
        "rankFixed": "03 D"
      },
      "D 04": {
        "image": "/i/cards-default/4D.svg",
        "suit": "D",
        "suitColor": "♦",
        "suitAlt": "4♦",
        "rank": "04",
        "rankA": "04",
        "rankFixed": "04 D"
      },
      "D 05": {
        "image": "/i/cards-default/5D.svg",
        "suit": "D",
        "suitColor": "♦",
        "suitAlt": "4♦",
        "rank": "05",
        "rankA": "05",
        "rankFixed": "05 D"
      },
      "D 06": {
        "image": "/i/cards-default/6D.svg",
        "suit": "D",
        "suitColor": "♦",
        "suitAlt": "4♦",
        "rank": "06",
        "rankA": "06",
        "rankFixed": "06 D"
      },
      "D 07": {
        "image": "/i/cards-default/7D.svg",
        "suit": "D",
        "suitColor": "♦",
        "suitAlt": "4♦",
        "rank": "07",
        "rankA": "07",
        "rankFixed": "07 D"
      },
      "D 08": {
        "image": "/i/cards-default/8D.svg",
        "suit": "D",
        "suitColor": "♦",
        "suitAlt": "4♦",
        "rank": "08",
        "rankA": "08",
        "rankFixed": "08 D"
      },
      "D 09": {
        "image": "/i/cards-default/9D.svg",
        "suit": "D",
        "suitColor": "♦",
        "suitAlt": "4♦",
        "rank": "09",
        "rankA": "09",
        "rankFixed": "09 D"
      },
      "D 10": {
        "image": "/i/cards-default/TD.svg",
        "suit": "D",
        "suitColor": "♦",
        "suitAlt": "4♦",
        "rank": "10",
        "rankA": "10",
        "rankFixed": "10 D"
      },
      "D 2J": {
        "image": "/i/cards-default/JD.svg",
        "suit": "D",
        "suitColor": "♦",
        "suitAlt": "4♦",
        "rank": "2J",
        "rankA": "2J",
        "rankFixed": "2J D"
      },
      "D 3Q": {
        "image": "/i/cards-default/QD.svg",
        "suit": "D",
        "suitColor": "♦",
        "suitAlt": "4♦",
        "rank": "3Q",
        "rankA": "3Q",
        "rankFixed": "3Q D"
      },
      "D 4K": {
        "image": "/i/cards-default/KD.svg",
        "suit": "D",
        "suitColor": "♦",
        "suitAlt": "4♦",
        "rank": "4K",
        "rankA": "4K",
        "rankFixed": "4K D"
      },
      "H 01": {
        "image": "/i/cards-default/AH.svg",
        "suit": "H",
        "suitColor": "♥",
        "suitAlt": "2♥",
        "rank": "01",
        "rankA": "5A",
        "rankFixed": "01 H"
      },
      "H 02": {
        "image": "/i/cards-default/2H.svg",
        "suit": "H",
        "suitColor": "♥",
        "suitAlt": "2♥",
        "rank": "02",
        "rankA": "02",
        "rankFixed": "02 H"
      },
      "H 03": {
        "image": "/i/cards-default/3H.svg",
        "suit": "H",
        "suitColor": "♥",
        "suitAlt": "2♥",
        "rank": "03",
        "rankA": "03",
        "rankFixed": "03 H"
      },
      "H 04": {
        "image": "/i/cards-default/4H.svg",
        "suit": "H",
        "suitColor": "♥",
        "suitAlt": "2♥",
        "rank": "04",
        "rankA": "04",
        "rankFixed": "04 H"
      },
      "H 05": {
        "image": "/i/cards-default/5H.svg",
        "suit": "H",
        "suitColor": "♥",
        "suitAlt": "2♥",
        "rank": "05",
        "rankA": "05",
        "rankFixed": "05 H"
      },
      "H 06": {
        "image": "/i/cards-default/6H.svg",
        "suit": "H",
        "suitColor": "♥",
        "suitAlt": "2♥",
        "rank": "06",
        "rankA": "06",
        "rankFixed": "06 H"
      },
      "H 07": {
        "image": "/i/cards-default/7H.svg",
        "suit": "H",
        "suitColor": "♥",
        "suitAlt": "2♥",
        "rank": "07",
        "rankA": "07",
        "rankFixed": "07 H"
      },
      "H 08": {
        "image": "/i/cards-default/8H.svg",
        "suit": "H",
        "suitColor": "♥",
        "suitAlt": "2♥",
        "rank": "08",
        "rankA": "08",
        "rankFixed": "08 H"
      },
      "H 09": {
        "image": "/i/cards-default/9H.svg",
        "suit": "H",
        "suitColor": "♥",
        "suitAlt": "2♥",
        "rank": "09",
        "rankA": "09",
        "rankFixed": "09 H"
      },
      "H 10": {
        "image": "/i/cards-default/TH.svg",
        "suit": "H",
        "suitColor": "♥",
        "suitAlt": "2♥",
        "rank": "10",
        "rankA": "10",
        "rankFixed": "10 H"
      },
      "H 2J": {
        "image": "/i/cards-default/JH.svg",
        "suit": "H",
        "suitColor": "♥",
        "suitAlt": "2♥",
        "rank": "2J",
        "rankA": "2J",
        "rankFixed": "2J H"
      },
      "H 3Q": {
        "image": "/i/cards-default/QH.svg",
        "suit": "H",
        "suitColor": "♥",
        "suitAlt": "2♥",
        "rank": "3Q",
        "rankA": "3Q",
        "rankFixed": "3Q H"
      },
      "H 4K": {
        "image": "/i/cards-default/KH.svg",
        "suit": "H",
        "suitColor": "♥",
        "suitAlt": "2♥",
        "rank": "4K",
        "rankA": "4K",
        "rankFixed": "4K H"
      },
      "S 01": {
        "image": "/i/cards-default/AS.svg",
        "suit": "S",
        "suitColor": "♠",
        "suitAlt": "3♠",
        "rank": "01",
        "rankA": "5A",
        "rankFixed": "01 S"
      },
      "S 02": {
        "image": "/i/cards-default/2S.svg",
        "suit": "S",
        "suitColor": "♠",
        "suitAlt": "3♠",
        "rank": "02",
        "rankA": "02",
        "rankFixed": "02 S"
      },
      "S 03": {
        "image": "/i/cards-default/3S.svg",
        "suit": "S",
        "suitColor": "♠",
        "suitAlt": "3♠",
        "rank": "03",
        "rankA": "03",
        "rankFixed": "03 S"
      },
      "S 04": {
        "image": "/i/cards-default/4S.svg",
        "suit": "S",
        "suitColor": "♠",
        "suitAlt": "3♠",
        "rank": "04",
        "rankA": "04",
        "rankFixed": "04 S"
      },
      "S 05": {
        "image": "/i/cards-default/5S.svg",
        "suit": "S",
        "suitColor": "♠",
        "suitAlt": "3♠",
        "rank": "05",
        "rankA": "05",
        "rankFixed": "05 S"
      },
      "S 06": {
        "image": "/i/cards-default/6S.svg",
        "suit": "S",
        "suitColor": "♠",
        "suitAlt": "3♠",
        "rank": "06",
        "rankA": "06",
        "rankFixed": "06 S"
      },
      "S 07": {
        "image": "/i/cards-default/7S.svg",
        "suit": "S",
        "suitColor": "♠",
        "suitAlt": "3♠",
        "rank": "07",
        "rankA": "07",
        "rankFixed": "07 S"
      },
      "S 08": {
        "image": "/i/cards-default/8S.svg",
        "suit": "S",
        "suitColor": "♠",
        "suitAlt": "3♠",
        "rank": "08",
        "rankA": "08",
        "rankFixed": "08 S"
      },
      "S 09": {
        "image": "/i/cards-default/9S.svg",
        "suit": "S",
        "suitColor": "♠",
        "suitAlt": "3♠",
        "rank": "09",
        "rankA": "09",
        "rankFixed": "09 S"
      },
      "S 10": {
        "image": "/i/cards-default/TS.svg",
        "suit": "S",
        "suitColor": "♠",
        "suitAlt": "3♠",
        "rank": "10",
        "rankA": "10",
        "rankFixed": "10 S"
      },
      "S 2J": {
        "image": "/i/cards-default/JS.svg",
        "suit": "S",
        "suitColor": "♠",
        "suitAlt": "3♠",
        "rank": "2J",
        "rankA": "2J",
        "rankFixed": "2J S"
      },
      "S 3Q": {
        "image": "/i/cards-default/QS.svg",
        "suit": "S",
        "suitColor": "♠",
        "suitAlt": "3♠",
        "rank": "3Q",
        "rankA": "3Q",
        "rankFixed": "3Q S"
      },
      "S 4K": {
        "image": "/i/cards-default/KS.svg",
        "suit": "S",
        "suitColor": "♠",
        "suitAlt": "3♠",
        "rank": "4K",
        "rankA": "4K",
        "rankFixed": "4K S"
      }
    },
    "faceTemplates": [
      {
        "border": false,
        "radius": false,
        "objects": [
          {
            "type": "image",
            "x": 0,
            "y": 0,
            "width": 103,
            "height": 160,
            "value": "/i/cards-default/2B.svg",
            "color": "transparent"
          }
        ]
      },
      {
        "border": false,
        "radius": false,
        "objects": [
          {
            "type": "image",
            "x": 0,
            "y": 0,
            "width": 103,
            "height": 160,
            "color": "transparent",
            "dynamicProperties": {
              "value": "image"
            }
          }
        ]
      }
    ],
    "cardDefaults": {
      "onPileCreation": {
        "handleCSS": ";background-color:transparent; background-image:url('/assets/-238645702_295'); background-size: contain; background-repeat: no-repeat;background-position: center;color:white",
        "clickRoutine": [
          {
            "func": "INPUT",
            "header": "Options for this pile ...",
            "fields": [
              {
                "type": "checkbox",
                "label": "Do you want to shuffle?",
                "variable": "shuffle",
                "value": true
              },
              {
                "type": "checkbox",
                "label": "Do you want to flip?",
                "variable": "flip",
                "value": true
              }
            ]
          },
          {
            "func": "IF",
            "operand1": "${shuffle}",
            "operand2": true,
            "thenRoutine": [
              {
                "func": "SELECT",
                "property": "parent",
                "value": "${thisID}"
              },
              {
                "func": "SHUFFLE"
              }
            ]
          },
          {
            "func": "IF",
            "operand1": "${flip}",
            "operand2": true,
            "thenRoutine": [
              {
                "func": "SELECT",
                "property": "parent",
                "value": "${thisID}"
              },
              {
                "func": "FLIP"
              }
            ]
          }
        ]
      }
    }
  },
  "7i0e_4_S": {
    "id": "7i0e_4_S",
    "deck": "7i0eD",
    "type": "card",
    "cardType": "S 04",
    "z": 5218,
    "parent": "ozrd"
  },
  "7i0e_5_S": {
    "id": "7i0e_5_S",
    "deck": "7i0eD",
    "type": "card",
    "cardType": "S 05",
    "z": 3674,
    "parent": "ozrd"
  },
  "7i0e_6_S": {
    "id": "7i0e_6_S",
    "deck": "7i0eD",
    "type": "card",
    "cardType": "S 06",
    "z": 8628,
    "parent": "ozrd"
  },
  "7i0e_7_S": {
    "id": "7i0e_7_S",
    "parent": "ozrd",
    "deck": "7i0eD",
    "type": "card",
    "cardType": "S 07",
    "z": 493
  },
  "7i0e_8_S": {
    "id": "7i0e_8_S",
    "deck": "7i0eD",
    "type": "card",
    "cardType": "S 08",
    "z": 4088,
    "parent": "ozrd"
  },
  "7i0e_9_S": {
    "id": "7i0e_9_S",
    "deck": "7i0eD",
    "type": "card",
    "cardType": "S 09",
    "z": 4734,
    "parent": "ozrd"
  },
  "7i0e_T_S": {
    "id": "7i0e_T_S",
    "deck": "7i0eD",
    "type": "card",
    "cardType": "S 10",
    "z": 3539,
    "parent": "ozrd"
  },
  "7i0e_J_S": {
    "id": "7i0e_J_S",
    "deck": "7i0eD",
    "type": "card",
    "cardType": "S 2J",
    "z": 3212,
    "parent": "ozrd"
  },
  "7i0e_Q_S": {
    "id": "7i0e_Q_S",
    "deck": "7i0eD",
    "type": "card",
    "cardType": "S 3Q",
    "z": 631,
    "parent": "ozrd"
  },
  "7i0e_K_S": {
    "id": "7i0e_K_S",
    "deck": "7i0eD",
    "type": "card",
    "cardType": "S 4K",
    "z": 9917,
    "parent": "ozrd"
  },
  "80vwB": {
    "id": "80vwB",
    "fixedParent": true,
    "y": 171.36,
    "width": 111,
    "height": 40,
    "type": "button",
    "text": "Recall & Shuffle",
    "movableInEdit": false,
    "clickRoutine": [
      {
        "func": "RECALL",
        "holder": "${PROPERTY parent}"
      },
      {
        "func": "FLIP",
        "holder": "${PROPERTY parent}",
        "face": 0
      },
      {
        "func": "SHUFFLE",
        "holder": "${PROPERTY parent}"
      }
    ],
    "parent": "staticHolder"
  },
  "80vwD": {
    "type": "deck",
    "id": "80vwD",
    "x": 12,
    "y": 41,
    "cardTypes": {
      "T 1J": {
        "image": "/i/cards-default/1J.svg",
        "suit": "T",
        "suitColor": "🃏",
        "suitAlt": "5J",
        "rank": "J1",
        "rankA": "J1",
        "rankFixed": "J1 T"
      },
      "T 2J": {
        "image": "/i/cards-default/2J.svg",
        "suit": "T",
        "suitColor": "🃏",
        "suitAlt": "5J",
        "rank": "J2",
        "rankA": "J2",
        "rankFixed": "J2 T"
      },
      "C 01": {
        "image": "/i/cards-default/AC.svg",
        "suit": "C",
        "suitColor": "♣",
        "suitAlt": "1♣",
        "rank": "01",
        "rankA": "5A",
        "rankFixed": "01 C"
      },
      "C 02": {
        "image": "/i/cards-default/2C.svg",
        "suit": "C",
        "suitColor": "♣",
        "suitAlt": "1♣",
        "rank": "02",
        "rankA": "02",
        "rankFixed": "02 C"
      },
      "C 03": {
        "image": "/i/cards-default/3C.svg",
        "suit": "C",
        "suitColor": "♣",
        "suitAlt": "1♣",
        "rank": "03",
        "rankA": "03",
        "rankFixed": "03 C"
      },
      "C 04": {
        "image": "/i/cards-default/4C.svg",
        "suit": "C",
        "suitColor": "♣",
        "suitAlt": "1♣",
        "rank": "04",
        "rankA": "04",
        "rankFixed": "04 C"
      },
      "C 05": {
        "image": "/i/cards-default/5C.svg",
        "suit": "C",
        "suitColor": "♣",
        "suitAlt": "1♣",
        "rank": "05",
        "rankA": "05",
        "rankFixed": "05 C"
      },
      "C 06": {
        "image": "/i/cards-default/6C.svg",
        "suit": "C",
        "suitColor": "♣",
        "suitAlt": "1♣",
        "rank": "06",
        "rankA": "06",
        "rankFixed": "06 C"
      },
      "C 07": {
        "image": "/i/cards-default/7C.svg",
        "suit": "C",
        "suitColor": "♣",
        "suitAlt": "1♣",
        "rank": "07",
        "rankA": "07",
        "rankFixed": "07 C"
      },
      "C 08": {
        "image": "/i/cards-default/8C.svg",
        "suit": "C",
        "suitColor": "♣",
        "suitAlt": "1♣",
        "rank": "08",
        "rankA": "08",
        "rankFixed": "08 C"
      },
      "C 09": {
        "image": "/i/cards-default/9C.svg",
        "suit": "C",
        "suitColor": "♣",
        "suitAlt": "1♣",
        "rank": "09",
        "rankA": "09",
        "rankFixed": "09 C"
      },
      "C 10": {
        "image": "/i/cards-default/TC.svg",
        "suit": "C",
        "suitColor": "♣",
        "suitAlt": "1♣",
        "rank": "10",
        "rankA": "10",
        "rankFixed": "10 C"
      },
      "C 2J": {
        "image": "/i/cards-default/JC.svg",
        "suit": "C",
        "suitColor": "♣",
        "suitAlt": "1♣",
        "rank": "2J",
        "rankA": "2J",
        "rankFixed": "2J C"
      },
      "C 3Q": {
        "image": "/i/cards-default/QC.svg",
        "suit": "C",
        "suitColor": "♣",
        "suitAlt": "1♣",
        "rank": "3Q",
        "rankA": "3Q",
        "rankFixed": "3Q C"
      },
      "C 4K": {
        "image": "/i/cards-default/KC.svg",
        "suit": "C",
        "suitColor": "♣",
        "suitAlt": "1♣",
        "rank": "4K",
        "rankA": "4K",
        "rankFixed": "4K C"
      },
      "D 01": {
        "image": "/i/cards-default/AD.svg",
        "suit": "D",
        "suitColor": "♦",
        "suitAlt": "4♦",
        "rank": "01",
        "rankA": "5A",
        "rankFixed": "01 D"
      },
      "D 02": {
        "image": "/i/cards-default/2D.svg",
        "suit": "D",
        "suitColor": "♦",
        "suitAlt": "4♦",
        "rank": "02",
        "rankA": "02",
        "rankFixed": "02 D"
      },
      "D 03": {
        "image": "/i/cards-default/3D.svg",
        "suit": "D",
        "suitColor": "♦",
        "suitAlt": "4♦",
        "rank": "03",
        "rankA": "03",
        "rankFixed": "03 D"
      },
      "D 04": {
        "image": "/i/cards-default/4D.svg",
        "suit": "D",
        "suitColor": "♦",
        "suitAlt": "4♦",
        "rank": "04",
        "rankA": "04",
        "rankFixed": "04 D"
      },
      "D 05": {
        "image": "/i/cards-default/5D.svg",
        "suit": "D",
        "suitColor": "♦",
        "suitAlt": "4♦",
        "rank": "05",
        "rankA": "05",
        "rankFixed": "05 D"
      },
      "D 06": {
        "image": "/i/cards-default/6D.svg",
        "suit": "D",
        "suitColor": "♦",
        "suitAlt": "4♦",
        "rank": "06",
        "rankA": "06",
        "rankFixed": "06 D"
      },
      "D 07": {
        "image": "/i/cards-default/7D.svg",
        "suit": "D",
        "suitColor": "♦",
        "suitAlt": "4♦",
        "rank": "07",
        "rankA": "07",
        "rankFixed": "07 D"
      },
      "D 08": {
        "image": "/i/cards-default/8D.svg",
        "suit": "D",
        "suitColor": "♦",
        "suitAlt": "4♦",
        "rank": "08",
        "rankA": "08",
        "rankFixed": "08 D"
      },
      "D 09": {
        "image": "/i/cards-default/9D.svg",
        "suit": "D",
        "suitColor": "♦",
        "suitAlt": "4♦",
        "rank": "09",
        "rankA": "09",
        "rankFixed": "09 D"
      },
      "D 10": {
        "image": "/i/cards-default/TD.svg",
        "suit": "D",
        "suitColor": "♦",
        "suitAlt": "4♦",
        "rank": "10",
        "rankA": "10",
        "rankFixed": "10 D"
      },
      "D 2J": {
        "image": "/i/cards-default/JD.svg",
        "suit": "D",
        "suitColor": "♦",
        "suitAlt": "4♦",
        "rank": "2J",
        "rankA": "2J",
        "rankFixed": "2J D"
      },
      "D 3Q": {
        "image": "/i/cards-default/QD.svg",
        "suit": "D",
        "suitColor": "♦",
        "suitAlt": "4♦",
        "rank": "3Q",
        "rankA": "3Q",
        "rankFixed": "3Q D"
      },
      "D 4K": {
        "image": "/i/cards-default/KD.svg",
        "suit": "D",
        "suitColor": "♦",
        "suitAlt": "4♦",
        "rank": "4K",
        "rankA": "4K",
        "rankFixed": "4K D"
      },
      "H 01": {
        "image": "/i/cards-default/AH.svg",
        "suit": "H",
        "suitColor": "♥",
        "suitAlt": "2♥",
        "rank": "01",
        "rankA": "5A",
        "rankFixed": "01 H"
      },
      "H 02": {
        "image": "/i/cards-default/2H.svg",
        "suit": "H",
        "suitColor": "♥",
        "suitAlt": "2♥",
        "rank": "02",
        "rankA": "02",
        "rankFixed": "02 H"
      },
      "H 03": {
        "image": "/i/cards-default/3H.svg",
        "suit": "H",
        "suitColor": "♥",
        "suitAlt": "2♥",
        "rank": "03",
        "rankA": "03",
        "rankFixed": "03 H"
      },
      "H 04": {
        "image": "/i/cards-default/4H.svg",
        "suit": "H",
        "suitColor": "♥",
        "suitAlt": "2♥",
        "rank": "04",
        "rankA": "04",
        "rankFixed": "04 H"
      },
      "H 05": {
        "image": "/i/cards-default/5H.svg",
        "suit": "H",
        "suitColor": "♥",
        "suitAlt": "2♥",
        "rank": "05",
        "rankA": "05",
        "rankFixed": "05 H"
      },
      "H 06": {
        "image": "/i/cards-default/6H.svg",
        "suit": "H",
        "suitColor": "♥",
        "suitAlt": "2♥",
        "rank": "06",
        "rankA": "06",
        "rankFixed": "06 H"
      },
      "H 07": {
        "image": "/i/cards-default/7H.svg",
        "suit": "H",
        "suitColor": "♥",
        "suitAlt": "2♥",
        "rank": "07",
        "rankA": "07",
        "rankFixed": "07 H"
      },
      "H 08": {
        "image": "/i/cards-default/8H.svg",
        "suit": "H",
        "suitColor": "♥",
        "suitAlt": "2♥",
        "rank": "08",
        "rankA": "08",
        "rankFixed": "08 H"
      },
      "H 09": {
        "image": "/i/cards-default/9H.svg",
        "suit": "H",
        "suitColor": "♥",
        "suitAlt": "2♥",
        "rank": "09",
        "rankA": "09",
        "rankFixed": "09 H"
      },
      "H 10": {
        "image": "/i/cards-default/TH.svg",
        "suit": "H",
        "suitColor": "♥",
        "suitAlt": "2♥",
        "rank": "10",
        "rankA": "10",
        "rankFixed": "10 H"
      },
      "H 2J": {
        "image": "/i/cards-default/JH.svg",
        "suit": "H",
        "suitColor": "♥",
        "suitAlt": "2♥",
        "rank": "2J",
        "rankA": "2J",
        "rankFixed": "2J H"
      },
      "H 3Q": {
        "image": "/i/cards-default/QH.svg",
        "suit": "H",
        "suitColor": "♥",
        "suitAlt": "2♥",
        "rank": "3Q",
        "rankA": "3Q",
        "rankFixed": "3Q H"
      },
      "H 4K": {
        "image": "/i/cards-default/KH.svg",
        "suit": "H",
        "suitColor": "♥",
        "suitAlt": "2♥",
        "rank": "4K",
        "rankA": "4K",
        "rankFixed": "4K H"
      },
      "S 01": {
        "image": "/i/cards-default/AS.svg",
        "suit": "S",
        "suitColor": "♠",
        "suitAlt": "3♠",
        "rank": "01",
        "rankA": "5A",
        "rankFixed": "01 S"
      },
      "S 02": {
        "image": "/i/cards-default/2S.svg",
        "suit": "S",
        "suitColor": "♠",
        "suitAlt": "3♠",
        "rank": "02",
        "rankA": "02",
        "rankFixed": "02 S"
      },
      "S 03": {
        "image": "/i/cards-default/3S.svg",
        "suit": "S",
        "suitColor": "♠",
        "suitAlt": "3♠",
        "rank": "03",
        "rankA": "03",
        "rankFixed": "03 S"
      },
      "S 04": {
        "image": "/i/cards-default/4S.svg",
        "suit": "S",
        "suitColor": "♠",
        "suitAlt": "3♠",
        "rank": "04",
        "rankA": "04",
        "rankFixed": "04 S"
      },
      "S 05": {
        "image": "/i/cards-default/5S.svg",
        "suit": "S",
        "suitColor": "♠",
        "suitAlt": "3♠",
        "rank": "05",
        "rankA": "05",
        "rankFixed": "05 S"
      },
      "S 06": {
        "image": "/i/cards-default/6S.svg",
        "suit": "S",
        "suitColor": "♠",
        "suitAlt": "3♠",
        "rank": "06",
        "rankA": "06",
        "rankFixed": "06 S"
      },
      "S 07": {
        "image": "/i/cards-default/7S.svg",
        "suit": "S",
        "suitColor": "♠",
        "suitAlt": "3♠",
        "rank": "07",
        "rankA": "07",
        "rankFixed": "07 S"
      },
      "S 08": {
        "image": "/i/cards-default/8S.svg",
        "suit": "S",
        "suitColor": "♠",
        "suitAlt": "3♠",
        "rank": "08",
        "rankA": "08",
        "rankFixed": "08 S"
      },
      "S 09": {
        "image": "/i/cards-default/9S.svg",
        "suit": "S",
        "suitColor": "♠",
        "suitAlt": "3♠",
        "rank": "09",
        "rankA": "09",
        "rankFixed": "09 S"
      },
      "S 10": {
        "image": "/i/cards-default/TS.svg",
        "suit": "S",
        "suitColor": "♠",
        "suitAlt": "3♠",
        "rank": "10",
        "rankA": "10",
        "rankFixed": "10 S"
      },
      "S 2J": {
        "image": "/i/cards-default/JS.svg",
        "suit": "S",
        "suitColor": "♠",
        "suitAlt": "3♠",
        "rank": "2J",
        "rankA": "2J",
        "rankFixed": "2J S"
      },
      "S 3Q": {
        "image": "/i/cards-default/QS.svg",
        "suit": "S",
        "suitColor": "♠",
        "suitAlt": "3♠",
        "rank": "3Q",
        "rankA": "3Q",
        "rankFixed": "3Q S"
      },
      "S 4K": {
        "image": "/i/cards-default/KS.svg",
        "suit": "S",
        "suitColor": "♠",
        "suitAlt": "3♠",
        "rank": "4K",
        "rankA": "4K",
        "rankFixed": "4K S"
      }
    },
    "faceTemplates": [
      {
        "border": false,
        "radius": false,
        "objects": [
          {
            "type": "image",
            "x": 0,
            "y": 0,
            "width": 103,
            "height": 160,
            "value": "/i/cards-default/2B.svg",
            "color": "transparent"
          }
        ]
      },
      {
        "border": false,
        "radius": false,
        "objects": [
          {
            "type": "image",
            "x": 0,
            "y": 0,
            "width": 103,
            "height": 160,
            "color": "transparent",
            "dynamicProperties": {
              "value": "image"
            }
          }
        ]
      }
    ],
    "cardDefaults": {
      "onPileCreation": {
        "handleCSS": "background:black;color:white; border-radius:35%",
        "parentGlobalUpdateRoutine": [
          {
            "func": "IF",
            "operand1": "${PROPERTY parent}",
            "operand2": "staticHolder",
            "thenRoutine": [
              {
                "func": "SET",
                "collection": "thisButton",
                "property": "handleCSS",
                "value": null
              }
            ]
          }
        ]
      }
    },
    "parent": "staticHolder"
  },
  "80vw_4_S": {
    "id": "80vw_4_S",
    "deck": "80vwD",
    "type": "card",
    "cardType": "S 04",
    "z": 8472,
    "parent": "7a8a"
  },
  "80vw_5_S": {
    "id": "80vw_5_S",
    "parent": "7a8a",
    "deck": "80vwD",
    "type": "card",
    "cardType": "S 05",
    "z": 4235
  },
  "80vw_6_S": {
    "id": "80vw_6_S",
    "deck": "80vwD",
    "type": "card",
    "cardType": "S 06",
    "z": 7621,
    "parent": "7a8a"
  },
  "80vw_7_S": {
    "id": "80vw_7_S",
    "deck": "80vwD",
    "type": "card",
    "cardType": "S 07",
    "z": 4687,
    "parent": "7a8a"
  },
  "80vw_8_S": {
    "id": "80vw_8_S",
    "deck": "80vwD",
    "type": "card",
    "cardType": "S 08",
    "z": 6266,
    "parent": "7a8a"
  },
  "80vw_9_S": {
    "id": "80vw_9_S",
    "deck": "80vwD",
    "type": "card",
    "cardType": "S 09",
    "z": 5340,
    "parent": "7a8a"
  },
  "80vw_T_S": {
    "id": "80vw_T_S",
    "deck": "80vwD",
    "type": "card",
    "cardType": "S 10",
    "z": 4397,
    "parent": "7a8a"
  },
  "80vw_J_S": {
    "id": "80vw_J_S",
    "deck": "80vwD",
    "type": "card",
    "cardType": "S 2J",
    "z": 3748,
    "parent": "7a8a"
  },
  "80vw_Q_S": {
    "id": "80vw_Q_S",
    "deck": "80vwD",
    "type": "card",
    "cardType": "S 3Q",
    "z": 9935,
    "parent": "7a8a"
  },
  "80vw_K_S": {
    "id": "80vw_K_S",
    "deck": "80vwD",
    "type": "card",
    "cardType": "S 4K",
    "z": 3880,
    "parent": "7a8a"
  },
  "staticHolder": {
    "type": "holder",
    "id": "staticHolder",
    "x": 744.5,
    "y": 769,
    "z": 49,
    "dropTarget": {
      "type": "card"
    }
  },
  "q9fg": {
    "id": "q9fg",
    "z": 94,
    "height": 30,
    "css": "font-size: 25px; ",
    "width": 40,
    "movable": false,
    "text": "4",
    "parent": "7i0e",
    "y": -50,
    "x": 35.5
  },
  "q10fg": {
    "id": "q10fg",
    "z": 95,
    "x": 35.5,
    "y": -50,
    "height": 30,
    "css": "font-size: 25px; ",
    "width": 40,
    "movable": false,
    "text": "5",
    "parent": "yxq7"
  },
  "q11fg": {
    "id": "q11fg",
    "z": 96,
    "x": 35.5,
    "y": -50,
    "height": 30,
    "css": "font-size: 25px; ",
    "width": 40,
    "movable": false,
    "text": "6",
    "parent": "7a8a"
  },
  "406b": {
    "id": "406b",
    "z": 96,
    "x": 46,
    "y": 100,
    "css": "font-size: 25px; ",
    "width": 1500,
    "height": 500,
    "text": "Piles can also have routines added to them such as 'clickRoutine' or 'enterRoutine'.\n\nDeck #4 creates a 'clickRoutine' on a pile. You can use the 'INPUT' function to customize what happens when a pile handle is clicked.  This particular input example allows a pile to be flipped and shuffled at the same time.  It also shows how to change the handle to an image. In this case a pentagon is shown. It may take some trial and error with the CSS to get the image to display properly.\n\nDeck #5 takes this a step further and automates what happens when the pile handle is clicked.  In this case, it spreads out the cards.  Click again and it puts them back in a pile.\n\nDeck #6 shows how you could make the piles on the floor different than the piles in the holder.  Create a new pile with a few cards to see.\n\nDeck #7 uses enter and leave routines to count the cards and change the color of the pile handle depending on the number of cards.  Less than 5 is green, 5-8 is orange, and 9-10 is red.\n\nDeck #8 shows how you can use an array of assets, that are displayed depending on the number of cards in a pile. In this case \"rank\" symbols are used.",
    "movable": false,
    "movableInEdit": false,
    "layer": -3
  },
  "q12fg": {
    "id": "q12fg",
    "z": 98,
    "x": 35.5,
    "y": -50,
    "height": 30,
    "css": "font-size: 25px; ",
    "width": 40,
    "movable": false,
    "text": "7",
    "parent": "4vw5"
  },
  "ozrd": {
    "type": "pile",
    "parent": "7i0e",
    "width": 103,
    "height": 160,
    "handleCSS": ";background-color:transparent; background-image:url('/assets/-238645702_295'); background-size: contain; background-repeat: no-repeat;background-position: center;color:white",
    "clickRoutine": [
      {
        "func": "INPUT",
        "header": "Options for this pile ...",
        "fields": [
          {
            "type": "checkbox",
            "label": "Do you want to shuffle?",
            "variable": "shuffle",
            "value": true
          },
          {
            "type": "checkbox",
            "label": "Do you want to flip?",
            "variable": "flip",
            "value": true
          }
        ]
      },
      {
        "func": "IF",
        "operand1": "${shuffle}",
        "operand2": true,
        "thenRoutine": [
          {
            "func": "SELECT",
            "property": "parent",
            "value": "${thisID}"
          },
          {
            "func": "SHUFFLE"
          }
        ]
      },
      {
        "func": "IF",
        "operand1": "${flip}",
        "operand2": true,
        "thenRoutine": [
          {
            "func": "SELECT",
            "property": "parent",
            "value": "${thisID}"
          },
          {
            "func": "FLIP"
          }
        ]
      }
    ],
    "id": "ozrd"
  },
  "mxep": {
    "type": "holder",
    "id": "mxep",
    "x": 1079.25,
    "y": 769,
    "dropTarget": {
      "type": "card"
    },
    "z": 99
  },
  "mxepB": {
    "id": "mxepB",
    "parent": "mxep",
    "fixedParent": true,
    "y": 171.36,
    "width": 111,
    "height": 40,
    "type": "button",
    "text": "Recall & Shuffle",
    "movableInEdit": false,
    "clickRoutine": [
      {
        "func": "RECALL",
        "holder": "${PROPERTY parent}"
      },
      {
        "func": "FLIP",
        "holder": "${PROPERTY parent}",
        "face": 0
      },
      {
        "func": "SHUFFLE",
        "holder": "${PROPERTY parent}"
      }
    ]
  },
  "mxepD": {
    "type": "deck",
    "id": "mxepD",
    "parent": "mxep",
    "x": 12,
    "y": 41,
    "cardTypes": {
      "T 1J": {
        "image": "/i/cards-default/1J.svg",
        "suit": "T",
        "suitColor": "🃏",
        "suitAlt": "5J",
        "rank": "J1",
        "rankA": "J1",
        "rankFixed": "J1 T"
      },
      "T 2J": {
        "image": "/i/cards-default/2J.svg",
        "suit": "T",
        "suitColor": "🃏",
        "suitAlt": "5J",
        "rank": "J2",
        "rankA": "J2",
        "rankFixed": "J2 T"
      },
      "C 01": {
        "image": "/i/cards-default/AC.svg",
        "suit": "C",
        "suitColor": "♣",
        "suitAlt": "1♣",
        "rank": "01",
        "rankA": "5A",
        "rankFixed": "01 C"
      },
      "C 02": {
        "image": "/i/cards-default/2C.svg",
        "suit": "C",
        "suitColor": "♣",
        "suitAlt": "1♣",
        "rank": "02",
        "rankA": "02",
        "rankFixed": "02 C"
      },
      "C 03": {
        "image": "/i/cards-default/3C.svg",
        "suit": "C",
        "suitColor": "♣",
        "suitAlt": "1♣",
        "rank": "03",
        "rankA": "03",
        "rankFixed": "03 C"
      },
      "C 04": {
        "image": "/i/cards-default/4C.svg",
        "suit": "C",
        "suitColor": "♣",
        "suitAlt": "1♣",
        "rank": "04",
        "rankA": "04",
        "rankFixed": "04 C"
      },
      "C 05": {
        "image": "/i/cards-default/5C.svg",
        "suit": "C",
        "suitColor": "♣",
        "suitAlt": "1♣",
        "rank": "05",
        "rankA": "05",
        "rankFixed": "05 C"
      },
      "C 06": {
        "image": "/i/cards-default/6C.svg",
        "suit": "C",
        "suitColor": "♣",
        "suitAlt": "1♣",
        "rank": "06",
        "rankA": "06",
        "rankFixed": "06 C"
      },
      "C 07": {
        "image": "/i/cards-default/7C.svg",
        "suit": "C",
        "suitColor": "♣",
        "suitAlt": "1♣",
        "rank": "07",
        "rankA": "07",
        "rankFixed": "07 C"
      },
      "C 08": {
        "image": "/i/cards-default/8C.svg",
        "suit": "C",
        "suitColor": "♣",
        "suitAlt": "1♣",
        "rank": "08",
        "rankA": "08",
        "rankFixed": "08 C"
      },
      "C 09": {
        "image": "/i/cards-default/9C.svg",
        "suit": "C",
        "suitColor": "♣",
        "suitAlt": "1♣",
        "rank": "09",
        "rankA": "09",
        "rankFixed": "09 C"
      },
      "C 10": {
        "image": "/i/cards-default/TC.svg",
        "suit": "C",
        "suitColor": "♣",
        "suitAlt": "1♣",
        "rank": "10",
        "rankA": "10",
        "rankFixed": "10 C"
      },
      "C 2J": {
        "image": "/i/cards-default/JC.svg",
        "suit": "C",
        "suitColor": "♣",
        "suitAlt": "1♣",
        "rank": "2J",
        "rankA": "2J",
        "rankFixed": "2J C"
      },
      "C 3Q": {
        "image": "/i/cards-default/QC.svg",
        "suit": "C",
        "suitColor": "♣",
        "suitAlt": "1♣",
        "rank": "3Q",
        "rankA": "3Q",
        "rankFixed": "3Q C"
      },
      "C 4K": {
        "image": "/i/cards-default/KC.svg",
        "suit": "C",
        "suitColor": "♣",
        "suitAlt": "1♣",
        "rank": "4K",
        "rankA": "4K",
        "rankFixed": "4K C"
      },
      "D 01": {
        "image": "/i/cards-default/AD.svg",
        "suit": "D",
        "suitColor": "♦",
        "suitAlt": "4♦",
        "rank": "01",
        "rankA": "5A",
        "rankFixed": "01 D"
      },
      "D 02": {
        "image": "/i/cards-default/2D.svg",
        "suit": "D",
        "suitColor": "♦",
        "suitAlt": "4♦",
        "rank": "02",
        "rankA": "02",
        "rankFixed": "02 D"
      },
      "D 03": {
        "image": "/i/cards-default/3D.svg",
        "suit": "D",
        "suitColor": "♦",
        "suitAlt": "4♦",
        "rank": "03",
        "rankA": "03",
        "rankFixed": "03 D"
      },
      "D 04": {
        "image": "/i/cards-default/4D.svg",
        "suit": "D",
        "suitColor": "♦",
        "suitAlt": "4♦",
        "rank": "04",
        "rankA": "04",
        "rankFixed": "04 D"
      },
      "D 05": {
        "image": "/i/cards-default/5D.svg",
        "suit": "D",
        "suitColor": "♦",
        "suitAlt": "4♦",
        "rank": "05",
        "rankA": "05",
        "rankFixed": "05 D"
      },
      "D 06": {
        "image": "/i/cards-default/6D.svg",
        "suit": "D",
        "suitColor": "♦",
        "suitAlt": "4♦",
        "rank": "06",
        "rankA": "06",
        "rankFixed": "06 D"
      },
      "D 07": {
        "image": "/i/cards-default/7D.svg",
        "suit": "D",
        "suitColor": "♦",
        "suitAlt": "4♦",
        "rank": "07",
        "rankA": "07",
        "rankFixed": "07 D"
      },
      "D 08": {
        "image": "/i/cards-default/8D.svg",
        "suit": "D",
        "suitColor": "♦",
        "suitAlt": "4♦",
        "rank": "08",
        "rankA": "08",
        "rankFixed": "08 D"
      },
      "D 09": {
        "image": "/i/cards-default/9D.svg",
        "suit": "D",
        "suitColor": "♦",
        "suitAlt": "4♦",
        "rank": "09",
        "rankA": "09",
        "rankFixed": "09 D"
      },
      "D 10": {
        "image": "/i/cards-default/TD.svg",
        "suit": "D",
        "suitColor": "♦",
        "suitAlt": "4♦",
        "rank": "10",
        "rankA": "10",
        "rankFixed": "10 D"
      },
      "D 2J": {
        "image": "/i/cards-default/JD.svg",
        "suit": "D",
        "suitColor": "♦",
        "suitAlt": "4♦",
        "rank": "2J",
        "rankA": "2J",
        "rankFixed": "2J D"
      },
      "D 3Q": {
        "image": "/i/cards-default/QD.svg",
        "suit": "D",
        "suitColor": "♦",
        "suitAlt": "4♦",
        "rank": "3Q",
        "rankA": "3Q",
        "rankFixed": "3Q D"
      },
      "D 4K": {
        "image": "/i/cards-default/KD.svg",
        "suit": "D",
        "suitColor": "♦",
        "suitAlt": "4♦",
        "rank": "4K",
        "rankA": "4K",
        "rankFixed": "4K D"
      },
      "H 01": {
        "image": "/i/cards-default/AH.svg",
        "suit": "H",
        "suitColor": "♥",
        "suitAlt": "2♥",
        "rank": "01",
        "rankA": "5A",
        "rankFixed": "01 H"
      },
      "H 02": {
        "image": "/i/cards-default/2H.svg",
        "suit": "H",
        "suitColor": "♥",
        "suitAlt": "2♥",
        "rank": "02",
        "rankA": "02",
        "rankFixed": "02 H"
      },
      "H 03": {
        "image": "/i/cards-default/3H.svg",
        "suit": "H",
        "suitColor": "♥",
        "suitAlt": "2♥",
        "rank": "03",
        "rankA": "03",
        "rankFixed": "03 H"
      },
      "H 04": {
        "image": "/i/cards-default/4H.svg",
        "suit": "H",
        "suitColor": "♥",
        "suitAlt": "2♥",
        "rank": "04",
        "rankA": "04",
        "rankFixed": "04 H"
      },
      "H 05": {
        "image": "/i/cards-default/5H.svg",
        "suit": "H",
        "suitColor": "♥",
        "suitAlt": "2♥",
        "rank": "05",
        "rankA": "05",
        "rankFixed": "05 H"
      },
      "H 06": {
        "image": "/i/cards-default/6H.svg",
        "suit": "H",
        "suitColor": "♥",
        "suitAlt": "2♥",
        "rank": "06",
        "rankA": "06",
        "rankFixed": "06 H"
      },
      "H 07": {
        "image": "/i/cards-default/7H.svg",
        "suit": "H",
        "suitColor": "♥",
        "suitAlt": "2♥",
        "rank": "07",
        "rankA": "07",
        "rankFixed": "07 H"
      },
      "H 08": {
        "image": "/i/cards-default/8H.svg",
        "suit": "H",
        "suitColor": "♥",
        "suitAlt": "2♥",
        "rank": "08",
        "rankA": "08",
        "rankFixed": "08 H"
      },
      "H 09": {
        "image": "/i/cards-default/9H.svg",
        "suit": "H",
        "suitColor": "♥",
        "suitAlt": "2♥",
        "rank": "09",
        "rankA": "09",
        "rankFixed": "09 H"
      },
      "H 10": {
        "image": "/i/cards-default/TH.svg",
        "suit": "H",
        "suitColor": "♥",
        "suitAlt": "2♥",
        "rank": "10",
        "rankA": "10",
        "rankFixed": "10 H"
      },
      "H 2J": {
        "image": "/i/cards-default/JH.svg",
        "suit": "H",
        "suitColor": "♥",
        "suitAlt": "2♥",
        "rank": "2J",
        "rankA": "2J",
        "rankFixed": "2J H"
      },
      "H 3Q": {
        "image": "/i/cards-default/QH.svg",
        "suit": "H",
        "suitColor": "♥",
        "suitAlt": "2♥",
        "rank": "3Q",
        "rankA": "3Q",
        "rankFixed": "3Q H"
      },
      "H 4K": {
        "image": "/i/cards-default/KH.svg",
        "suit": "H",
        "suitColor": "♥",
        "suitAlt": "2♥",
        "rank": "4K",
        "rankA": "4K",
        "rankFixed": "4K H"
      },
      "S 01": {
        "image": "/i/cards-default/AS.svg",
        "suit": "S",
        "suitColor": "♠",
        "suitAlt": "3♠",
        "rank": "01",
        "rankA": "5A",
        "rankFixed": "01 S"
      },
      "S 02": {
        "image": "/i/cards-default/2S.svg",
        "suit": "S",
        "suitColor": "♠",
        "suitAlt": "3♠",
        "rank": "02",
        "rankA": "02",
        "rankFixed": "02 S"
      },
      "S 03": {
        "image": "/i/cards-default/3S.svg",
        "suit": "S",
        "suitColor": "♠",
        "suitAlt": "3♠",
        "rank": "03",
        "rankA": "03",
        "rankFixed": "03 S"
      },
      "S 04": {
        "image": "/i/cards-default/4S.svg",
        "suit": "S",
        "suitColor": "♠",
        "suitAlt": "3♠",
        "rank": "04",
        "rankA": "04",
        "rankFixed": "04 S"
      },
      "S 05": {
        "image": "/i/cards-default/5S.svg",
        "suit": "S",
        "suitColor": "♠",
        "suitAlt": "3♠",
        "rank": "05",
        "rankA": "05",
        "rankFixed": "05 S"
      },
      "S 06": {
        "image": "/i/cards-default/6S.svg",
        "suit": "S",
        "suitColor": "♠",
        "suitAlt": "3♠",
        "rank": "06",
        "rankA": "06",
        "rankFixed": "06 S"
      },
      "S 07": {
        "image": "/i/cards-default/7S.svg",
        "suit": "S",
        "suitColor": "♠",
        "suitAlt": "3♠",
        "rank": "07",
        "rankA": "07",
        "rankFixed": "07 S"
      },
      "S 08": {
        "image": "/i/cards-default/8S.svg",
        "suit": "S",
        "suitColor": "♠",
        "suitAlt": "3♠",
        "rank": "08",
        "rankA": "08",
        "rankFixed": "08 S"
      },
      "S 09": {
        "image": "/i/cards-default/9S.svg",
        "suit": "S",
        "suitColor": "♠",
        "suitAlt": "3♠",
        "rank": "09",
        "rankA": "09",
        "rankFixed": "09 S"
      },
      "S 10": {
        "image": "/i/cards-default/TS.svg",
        "suit": "S",
        "suitColor": "♠",
        "suitAlt": "3♠",
        "rank": "10",
        "rankA": "10",
        "rankFixed": "10 S"
      },
      "S 2J": {
        "image": "/i/cards-default/JS.svg",
        "suit": "S",
        "suitColor": "♠",
        "suitAlt": "3♠",
        "rank": "2J",
        "rankA": "2J",
        "rankFixed": "2J S"
      },
      "S 3Q": {
        "image": "/i/cards-default/QS.svg",
        "suit": "S",
        "suitColor": "♠",
        "suitAlt": "3♠",
        "rank": "3Q",
        "rankA": "3Q",
        "rankFixed": "3Q S"
      },
      "S 4K": {
        "image": "/i/cards-default/KS.svg",
        "suit": "S",
        "suitColor": "♠",
        "suitAlt": "3♠",
        "rank": "4K",
        "rankA": "4K",
        "rankFixed": "4K S"
      }
    },
    "faceTemplates": [
      {
        "border": false,
        "radius": false,
        "objects": [
          {
            "type": "image",
            "x": 0,
            "y": 0,
            "width": 103,
            "height": 160,
            "value": "/i/cards-default/2B.svg",
            "color": "transparent"
          }
        ]
      },
      {
        "border": false,
        "radius": false,
        "objects": [
          {
            "type": "image",
            "x": 0,
            "y": 0,
            "width": 103,
            "height": 160,
            "color": "transparent",
            "dynamicProperties": {
              "value": "image"
            }
          }
        ]
      }
    ],
    "cardDefaults": {
      "onPileCreation": {
        "handleCSS": "background:green;color:white",
        "setColorRoutine": [
          {
            "func": "SELECT",
            "property": "parent",
            "value": "${thisID}"
          },
          {
            "func": "COUNT"
          },
          {
            "func": "IF",
            "operand1": "${COUNT}",
            "operand2": 9,
            "relation": "<",
            "thenRoutine": [
              {
                "func": "SET",
                "collection": [
                  "${thisID}"
                ],
                "property": "handleCSS",
                "value": "background:orange;color:white"
              },
              {
                "func": "IF",
                "operand1": "${COUNT}",
                "operand2": 5,
                "relation": "<",
                "thenRoutine": [
                  {
                    "func": "SET",
                    "collection": [
                      "${thisID}"
                    ],
                    "property": "handleCSS",
                    "value": "background:green;color:white"
                  }
                ]
              }
            ],
            "elseRoutine": [
              {
                "func": "SET",
                "collection": [
                  "${thisID}"
                ],
                "property": "handleCSS",
                "value": "background:red;color:white"
              }
            ]
          }
        ],
        "enterRoutine": [
          {
            "func": "CALL",
            "routine": "setColorRoutine"
          }
        ],
        "leaveRoutine": [
          {
            "func": "CALL",
            "routine": "setColorRoutine"
          }
        ]
      }
    }
  },
  "mxep_4_S": {
    "id": "mxep_4_S",
    "deck": "mxepD",
    "type": "card",
    "cardType": "S 04",
    "z": 10049,
    "parent": "4vw5"
  },
  "mxep_5_S": {
    "id": "mxep_5_S",
    "deck": "mxepD",
    "type": "card",
    "cardType": "S 05",
    "z": 10011,
    "parent": "4vw5"
  },
  "mxep_6_S": {
    "id": "mxep_6_S",
    "deck": "mxepD",
    "type": "card",
    "cardType": "S 06",
    "z": 10013,
    "parent": "4vw5"
  },
  "mxep_7_S": {
    "id": "mxep_7_S",
    "deck": "mxepD",
    "type": "card",
    "cardType": "S 07",
    "z": 10019,
    "parent": "4vw5"
  },
  "mxep_8_S": {
    "id": "mxep_8_S",
    "deck": "mxepD",
    "type": "card",
    "cardType": "S 08",
    "z": 10018,
    "parent": "4vw5"
  },
  "mxep_9_S": {
    "id": "mxep_9_S",
    "deck": "mxepD",
    "type": "card",
    "cardType": "S 09",
    "z": 10014,
    "parent": "4vw5"
  },
  "mxep_T_S": {
    "id": "mxep_T_S",
    "deck": "mxepD",
    "type": "card",
    "cardType": "S 10",
    "z": 10017,
    "parent": "4vw5"
  },
  "mxep_J_S": {
    "id": "mxep_J_S",
    "deck": "mxepD",
    "type": "card",
    "cardType": "S 2J",
    "z": 10016,
    "parent": "4vw5"
  },
  "mxep_Q_S": {
    "id": "mxep_Q_S",
    "deck": "mxepD",
    "type": "card",
    "cardType": "S 3Q",
    "z": 10012,
    "parent": "4vw5"
  },
  "mxep_K_S": {
    "id": "mxep_K_S",
    "deck": "mxepD",
    "type": "card",
    "cardType": "S 4K",
    "z": 10015,
    "parent": "4vw5"
  },
  "7a8a": {
    "type": "pile",
    "parent": "staticHolder",
    "width": 103,
    "height": 160,
    "parentGlobalUpdateRoutine": [
      {
        "func": "IF",
        "operand1": "${PROPERTY parent}",
        "operand2": "staticHolder",
        "thenRoutine": [
          {
            "func": "SET",
            "collection": "thisButton",
            "property": "handleCSS",
            "value": null
          }
        ]
      }
    ],
    "id": "7a8a"
  },
  "hzsu": {
    "type": "pile",
    "parent": "yxq7",
    "width": 103,
    "height": 160,
    "handleCSS": "background:blue; color:white",
    "clickRoutine": [
      {
        "func": "CALL",
        "routine": "expandRoutine"
      }
    ],
    "expandRoutine": [
      {
        "func": "SELECT",
        "property": "id",
        "value": "${thisID}"
      },
      {
        "func": "SORT",
        "key": "z"
      },
      {
        "func": "IF",
        "operand1": "${PROPERTY expanded}",
        "operand2": true,
        "relation": "!=",
        "thenRoutine": [
          "var xPos = 0",
          {
            "func": "FOREACH",
            "collection": "DEFAULT",
            "loopRoutine": [
              {
                "func": "SET",
                "collection": [
                  "${widgetID}"
                ],
                "property": "x",
                "value": "${xPos}"
              },
              "var xPos = ${xPos} - 35"
            ]
          },
          {
            "func": "SET",
            "property": "expanded",
            "collection": "thisButton",
            "value": true
          }
        ],
        "elseRoutine": [
          "var xPos = 0",
          {
            "func": "FOREACH",
            "collection": "DEFAULT",
            "loopRoutine": [
              {
                "func": "SET",
                "collection": [
                  "${widgetID}"
                ],
                "property": "x",
                "value": "${xPos}"
              }
            ]
          },
          {
            "func": "SET",
            "property": "expanded",
            "collection": "thisButton",
            "value": false
          }
        ]
      }
    ],
    "id": "hzsu",
    "expanded": true
  },
  "mxep1": {
    "type": "holder",
    "id": "mxep1",
    "x": 1414,
    "y": 769,
    "dropTarget": {
      "type": "card"
    },
    "z": 99,
    "task": "rankPile",
    "onEnter": {
      "activeFace": 1
    }
  },
  "mxepB1": {
    "id": "mxepB1",
    "parent": "mxep1",
    "fixedParent": true,
    "y": 171.36,
    "width": 111,
    "height": 40,
    "type": "button",
    "text": "Recall & Shuffle",
    "movableInEdit": false,
    "clickRoutine": [
      {
        "func": "RECALL",
        "holder": "${PROPERTY parent}"
      },
      {
        "func": "FLIP",
        "holder": "${PROPERTY parent}",
        "face": 0
      },
      {
        "func": "SHUFFLE",
        "holder": "${PROPERTY parent}"
      }
    ]
  },
  "mxepD1": {
    "type": "deck",
    "id": "mxepD1",
    "parent": "mxep1",
    "x": 12,
    "y": 41,
    "cardTypes": {
      "T 1J": {
        "image": "/i/cards-default/1J.svg",
        "suit": "T",
        "suitColor": "🃏",
        "suitAlt": "5J",
        "rank": "J1",
        "rankA": "J1",
        "rankFixed": "J1 T"
      },
      "T 2J": {
        "image": "/i/cards-default/2J.svg",
        "suit": "T",
        "suitColor": "🃏",
        "suitAlt": "5J",
        "rank": "J2",
        "rankA": "J2",
        "rankFixed": "J2 T"
      },
      "C 01": {
        "image": "/i/cards-default/AC.svg",
        "suit": "C",
        "suitColor": "♣",
        "suitAlt": "1♣",
        "rank": "01",
        "rankA": "5A",
        "rankFixed": "01 C"
      },
      "C 02": {
        "image": "/i/cards-default/2C.svg",
        "suit": "C",
        "suitColor": "♣",
        "suitAlt": "1♣",
        "rank": "02",
        "rankA": "02",
        "rankFixed": "02 C"
      },
      "C 03": {
        "image": "/i/cards-default/3C.svg",
        "suit": "C",
        "suitColor": "♣",
        "suitAlt": "1♣",
        "rank": "03",
        "rankA": "03",
        "rankFixed": "03 C"
      },
      "C 04": {
        "image": "/i/cards-default/4C.svg",
        "suit": "C",
        "suitColor": "♣",
        "suitAlt": "1♣",
        "rank": "04",
        "rankA": "04",
        "rankFixed": "04 C"
      },
      "C 05": {
        "image": "/i/cards-default/5C.svg",
        "suit": "C",
        "suitColor": "♣",
        "suitAlt": "1♣",
        "rank": "05",
        "rankA": "05",
        "rankFixed": "05 C"
      },
      "C 06": {
        "image": "/i/cards-default/6C.svg",
        "suit": "C",
        "suitColor": "♣",
        "suitAlt": "1♣",
        "rank": "06",
        "rankA": "06",
        "rankFixed": "06 C"
      },
      "C 07": {
        "image": "/i/cards-default/7C.svg",
        "suit": "C",
        "suitColor": "♣",
        "suitAlt": "1♣",
        "rank": "07",
        "rankA": "07",
        "rankFixed": "07 C"
      },
      "C 08": {
        "image": "/i/cards-default/8C.svg",
        "suit": "C",
        "suitColor": "♣",
        "suitAlt": "1♣",
        "rank": "08",
        "rankA": "08",
        "rankFixed": "08 C"
      },
      "C 09": {
        "image": "/i/cards-default/9C.svg",
        "suit": "C",
        "suitColor": "♣",
        "suitAlt": "1♣",
        "rank": "09",
        "rankA": "09",
        "rankFixed": "09 C"
      },
      "C 10": {
        "image": "/i/cards-default/TC.svg",
        "suit": "C",
        "suitColor": "♣",
        "suitAlt": "1♣",
        "rank": "10",
        "rankA": "10",
        "rankFixed": "10 C"
      },
      "C 2J": {
        "image": "/i/cards-default/JC.svg",
        "suit": "C",
        "suitColor": "♣",
        "suitAlt": "1♣",
        "rank": "2J",
        "rankA": "2J",
        "rankFixed": "2J C"
      },
      "C 3Q": {
        "image": "/i/cards-default/QC.svg",
        "suit": "C",
        "suitColor": "♣",
        "suitAlt": "1♣",
        "rank": "3Q",
        "rankA": "3Q",
        "rankFixed": "3Q C"
      },
      "C 4K": {
        "image": "/i/cards-default/KC.svg",
        "suit": "C",
        "suitColor": "♣",
        "suitAlt": "1♣",
        "rank": "4K",
        "rankA": "4K",
        "rankFixed": "4K C"
      },
      "D 01": {
        "image": "/i/cards-default/AD.svg",
        "suit": "D",
        "suitColor": "♦",
        "suitAlt": "4♦",
        "rank": "01",
        "rankA": "5A",
        "rankFixed": "01 D"
      },
      "D 02": {
        "image": "/i/cards-default/2D.svg",
        "suit": "D",
        "suitColor": "♦",
        "suitAlt": "4♦",
        "rank": "02",
        "rankA": "02",
        "rankFixed": "02 D"
      },
      "D 03": {
        "image": "/i/cards-default/3D.svg",
        "suit": "D",
        "suitColor": "♦",
        "suitAlt": "4♦",
        "rank": "03",
        "rankA": "03",
        "rankFixed": "03 D"
      },
      "D 04": {
        "image": "/i/cards-default/4D.svg",
        "suit": "D",
        "suitColor": "♦",
        "suitAlt": "4♦",
        "rank": "04",
        "rankA": "04",
        "rankFixed": "04 D"
      },
      "D 05": {
        "image": "/i/cards-default/5D.svg",
        "suit": "D",
        "suitColor": "♦",
        "suitAlt": "4♦",
        "rank": "05",
        "rankA": "05",
        "rankFixed": "05 D"
      },
      "D 06": {
        "image": "/i/cards-default/6D.svg",
        "suit": "D",
        "suitColor": "♦",
        "suitAlt": "4♦",
        "rank": "06",
        "rankA": "06",
        "rankFixed": "06 D"
      },
      "D 07": {
        "image": "/i/cards-default/7D.svg",
        "suit": "D",
        "suitColor": "♦",
        "suitAlt": "4♦",
        "rank": "07",
        "rankA": "07",
        "rankFixed": "07 D"
      },
      "D 08": {
        "image": "/i/cards-default/8D.svg",
        "suit": "D",
        "suitColor": "♦",
        "suitAlt": "4♦",
        "rank": "08",
        "rankA": "08",
        "rankFixed": "08 D"
      },
      "D 09": {
        "image": "/i/cards-default/9D.svg",
        "suit": "D",
        "suitColor": "♦",
        "suitAlt": "4♦",
        "rank": "09",
        "rankA": "09",
        "rankFixed": "09 D"
      },
      "D 10": {
        "image": "/i/cards-default/TD.svg",
        "suit": "D",
        "suitColor": "♦",
        "suitAlt": "4♦",
        "rank": "10",
        "rankA": "10",
        "rankFixed": "10 D"
      },
      "D 2J": {
        "image": "/i/cards-default/JD.svg",
        "suit": "D",
        "suitColor": "♦",
        "suitAlt": "4♦",
        "rank": "2J",
        "rankA": "2J",
        "rankFixed": "2J D"
      },
      "D 3Q": {
        "image": "/i/cards-default/QD.svg",
        "suit": "D",
        "suitColor": "♦",
        "suitAlt": "4♦",
        "rank": "3Q",
        "rankA": "3Q",
        "rankFixed": "3Q D"
      },
      "D 4K": {
        "image": "/i/cards-default/KD.svg",
        "suit": "D",
        "suitColor": "♦",
        "suitAlt": "4♦",
        "rank": "4K",
        "rankA": "4K",
        "rankFixed": "4K D"
      },
      "H 01": {
        "image": "/i/cards-default/AH.svg",
        "suit": "H",
        "suitColor": "♥",
        "suitAlt": "2♥",
        "rank": "01",
        "rankA": "5A",
        "rankFixed": "01 H"
      },
      "H 02": {
        "image": "/i/cards-default/2H.svg",
        "suit": "H",
        "suitColor": "♥",
        "suitAlt": "2♥",
        "rank": "02",
        "rankA": "02",
        "rankFixed": "02 H"
      },
      "H 03": {
        "image": "/i/cards-default/3H.svg",
        "suit": "H",
        "suitColor": "♥",
        "suitAlt": "2♥",
        "rank": "03",
        "rankA": "03",
        "rankFixed": "03 H"
      },
      "H 04": {
        "image": "/i/cards-default/4H.svg",
        "suit": "H",
        "suitColor": "♥",
        "suitAlt": "2♥",
        "rank": "04",
        "rankA": "04",
        "rankFixed": "04 H"
      },
      "H 05": {
        "image": "/i/cards-default/5H.svg",
        "suit": "H",
        "suitColor": "♥",
        "suitAlt": "2♥",
        "rank": "05",
        "rankA": "05",
        "rankFixed": "05 H"
      },
      "H 06": {
        "image": "/i/cards-default/6H.svg",
        "suit": "H",
        "suitColor": "♥",
        "suitAlt": "2♥",
        "rank": "06",
        "rankA": "06",
        "rankFixed": "06 H"
      },
      "H 07": {
        "image": "/i/cards-default/7H.svg",
        "suit": "H",
        "suitColor": "♥",
        "suitAlt": "2♥",
        "rank": "07",
        "rankA": "07",
        "rankFixed": "07 H"
      },
      "H 08": {
        "image": "/i/cards-default/8H.svg",
        "suit": "H",
        "suitColor": "♥",
        "suitAlt": "2♥",
        "rank": "08",
        "rankA": "08",
        "rankFixed": "08 H"
      },
      "H 09": {
        "image": "/i/cards-default/9H.svg",
        "suit": "H",
        "suitColor": "♥",
        "suitAlt": "2♥",
        "rank": "09",
        "rankA": "09",
        "rankFixed": "09 H"
      },
      "H 10": {
        "image": "/i/cards-default/TH.svg",
        "suit": "H",
        "suitColor": "♥",
        "suitAlt": "2♥",
        "rank": "10",
        "rankA": "10",
        "rankFixed": "10 H"
      },
      "H 2J": {
        "image": "/i/cards-default/JH.svg",
        "suit": "H",
        "suitColor": "♥",
        "suitAlt": "2♥",
        "rank": "2J",
        "rankA": "2J",
        "rankFixed": "2J H"
      },
      "H 3Q": {
        "image": "/i/cards-default/QH.svg",
        "suit": "H",
        "suitColor": "♥",
        "suitAlt": "2♥",
        "rank": "3Q",
        "rankA": "3Q",
        "rankFixed": "3Q H"
      },
      "H 4K": {
        "image": "/i/cards-default/KH.svg",
        "suit": "H",
        "suitColor": "♥",
        "suitAlt": "2♥",
        "rank": "4K",
        "rankA": "4K",
        "rankFixed": "4K H"
      },
      "S 01": {
        "image": "/i/cards-default/AS.svg",
        "suit": "S",
        "suitColor": "♠",
        "suitAlt": "3♠",
        "rank": "01",
        "rankA": "5A",
        "rankFixed": "01 S"
      },
      "S 02": {
        "image": "/i/cards-default/2S.svg",
        "suit": "S",
        "suitColor": "♠",
        "suitAlt": "3♠",
        "rank": "02",
        "rankA": "02",
        "rankFixed": "02 S"
      },
      "S 03": {
        "image": "/i/cards-default/3S.svg",
        "suit": "S",
        "suitColor": "♠",
        "suitAlt": "3♠",
        "rank": "03",
        "rankA": "03",
        "rankFixed": "03 S"
      },
      "S 04": {
        "image": "/i/cards-default/4S.svg",
        "suit": "S",
        "suitColor": "♠",
        "suitAlt": "3♠",
        "rank": "04",
        "rankA": "04",
        "rankFixed": "04 S"
      },
      "S 05": {
        "image": "/i/cards-default/5S.svg",
        "suit": "S",
        "suitColor": "♠",
        "suitAlt": "3♠",
        "rank": "05",
        "rankA": "05",
        "rankFixed": "05 S"
      },
      "S 06": {
        "image": "/i/cards-default/6S.svg",
        "suit": "S",
        "suitColor": "♠",
        "suitAlt": "3♠",
        "rank": "06",
        "rankA": "06",
        "rankFixed": "06 S"
      },
      "S 07": {
        "image": "/i/cards-default/7S.svg",
        "suit": "S",
        "suitColor": "♠",
        "suitAlt": "3♠",
        "rank": "07",
        "rankA": "07",
        "rankFixed": "07 S"
      },
      "S 08": {
        "image": "/i/cards-default/8S.svg",
        "suit": "S",
        "suitColor": "♠",
        "suitAlt": "3♠",
        "rank": "08",
        "rankA": "08",
        "rankFixed": "08 S"
      },
      "S 09": {
        "image": "/i/cards-default/9S.svg",
        "suit": "S",
        "suitColor": "♠",
        "suitAlt": "3♠",
        "rank": "09",
        "rankA": "09",
        "rankFixed": "09 S"
      },
      "S 10": {
        "image": "/i/cards-default/TS.svg",
        "suit": "S",
        "suitColor": "♠",
        "suitAlt": "3♠",
        "rank": "10",
        "rankA": "10",
        "rankFixed": "10 S"
      },
      "S 2J": {
        "image": "/i/cards-default/JS.svg",
        "suit": "S",
        "suitColor": "♠",
        "suitAlt": "3♠",
        "rank": "2J",
        "rankA": "2J",
        "rankFixed": "2J S"
      },
      "S 3Q": {
        "image": "/i/cards-default/QS.svg",
        "suit": "S",
        "suitColor": "♠",
        "suitAlt": "3♠",
        "rank": "3Q",
        "rankA": "3Q",
        "rankFixed": "3Q S"
      },
      "S 4K": {
        "image": "/i/cards-default/KS.svg",
        "suit": "S",
        "suitColor": "♠",
        "suitAlt": "3♠",
        "rank": "4K",
        "rankA": "4K",
        "rankFixed": "4K S"
      }
    },
    "faceTemplates": [
      {
        "border": false,
        "radius": false,
        "objects": [
          {
            "type": "image",
            "x": 0,
            "y": 0,
            "width": 103,
            "height": 160,
            "value": "/i/cards-default/2B.svg",
            "color": "transparent"
          }
        ]
      },
      {
        "border": false,
        "radius": false,
        "objects": [
          {
            "type": "image",
            "x": 0,
            "y": 0,
            "width": 103,
            "height": 160,
            "color": "transparent",
            "dynamicProperties": {
              "value": "image"
            }
          }
        ]
      }
    ],
    "cardDefaults": {
      "onPileCreation": {
        "images": [
          "this index remains without asset because to form a pile you need 2 cards, so the first asset needs to be at index 2",
          "this index remains without asset because to form a pile you need 2 cards, so the first asset needs to be at index 2",
          "/assets/-1928340783_3375",
          "/assets/-1871562056_4722",
          "/assets/1154117175_5888",
          "/assets/1896260709_9178",
          "/assets/-421841696_11837"
        ],
        "rankCSS": {
          "background-image": "url(assets/-1871562056_4722)",
          "background-size": "20px",
          "background-color": "transparent",
          "top": "5px",
          "left": "75px",
          "width": "20px",
          "height": "32.031872508px",
          "border-radius": "0px",
          "color": "transparent"
        },
        "leaveRoutine": [
          {
            "func": "CALL",
            "routine": "enterRoutine"
          }
        ],
        "enterRoutine": [
          {
            "func": "GET",
            "property": "task",
            "variable": "task",
            "collection": [
              "${PROPERTY parent}"
            ]
          },
          {
            "func": "IF",
            "operand1": "${task}",
            "operand2": "rankPile",
            "thenRoutine": [
              {
                "func": "COUNT",
                "holder": "${thisID}"
              },
              "var images = ${PROPERTY images}",
              "var image = ${images.$COUNT}",
              "var rankCSS = ${PROPERTY rankCSS}",
              "var BG = 'url(' + ${image}",
              "var BG = ${BG} + ')'",
              "var rankCSS.background-image = ${BG}",
              {
                "func": "SET",
                "property": "handleCSS",
                "value": "${rankCSS}",
                "collection": "thisButton"
              }
            ],
            "elseRoutine": [
              {
                "func": "SET",
                "property": "handleCSS",
                "value": null,
                "collection": "thisButton"
              }
            ]
          }
        ]
      }
    }
  },
  "4vw5": {
    "type": "pile",
    "parent": "mxep",
    "x": 4,
    "y": 4,
    "width": 103,
    "height": 160,
    "handleCSS": "background:red;color:white",
    "setColorRoutine": [
      {
        "func": "SELECT",
        "property": "parent",
        "value": "${thisID}"
      },
      {
        "func": "COUNT"
      },
      {
        "func": "IF",
        "operand1": "${COUNT}",
        "operand2": 9,
        "relation": "<",
        "thenRoutine": [
          {
            "func": "SET",
            "collection": [
              "${thisID}"
            ],
            "property": "handleCSS",
            "value": "background:orange;color:white"
          },
          {
            "func": "IF",
            "operand1": "${COUNT}",
            "operand2": 5,
            "relation": "<",
            "thenRoutine": [
              {
                "func": "SET",
                "collection": [
                  "${thisID}"
                ],
                "property": "handleCSS",
                "value": "background:green;color:white"
              }
            ]
          }
        ],
        "elseRoutine": [
          {
            "func": "SET",
            "collection": [
              "${thisID}"
            ],
            "property": "handleCSS",
            "value": "background:red;color:white"
          }
        ]
      }
    ],
    "enterRoutine": [
      {
        "func": "CALL",
        "routine": "setColorRoutine"
      }
    ],
    "leaveRoutine": [
      {
        "func": "CALL",
        "routine": "setColorRoutine"
      }
    ],
    "id": "4vw5"
  },
  "q13fg": {
    "id": "q13fg",
    "z": 98,
    "x": 35.5,
    "y": -50,
    "height": 30,
    "css": "font-size: 25px; ",
    "width": 40,
    "movable": false,
    "parent": "mxep1",
    "text": "8"
  },
  "yy4j": {
    "deck": "mxepD1",
    "type": "card",
    "cardType": "T 1J",
    "id": "yy4j",
    "z": 10121,
    "parent": "25e2",
    "activeFace": 1
  },
  "yn8o": {
    "deck": "mxepD1",
    "type": "card",
    "cardType": "T 2J",
    "id": "yn8o",
    "z": 10117,
    "activeFace": 1,
    "parent": "25e2"
  },
  "gww6": {
    "deck": "mxepD1",
    "type": "card",
    "cardType": "C 01",
    "id": "gww6",
    "z": 10120,
    "parent": "25e2",
    "activeFace": 1
  },
  "no7t": {
    "deck": "mxepD1",
    "type": "card",
    "cardType": "C 02",
    "id": "no7t",
    "z": 10119,
    "parent": "25e2",
    "activeFace": 1
  },
  "7mqu": {
    "deck": "mxepD1",
    "type": "card",
    "cardType": "C 03",
    "id": "7mqu",
    "z": 10118,
    "parent": "25e2",
    "activeFace": 1
  },
  "25e2": {
    "type": "pile",
    "width": 103,
    "height": 160,
    "images": [
      "this index remains without asset because to form a pile you need 2 cards, so the first asset needs to be at index 2",
      "this index remains without asset because to form a pile you need 2 cards, so the first asset needs to be at index 2",
      "/assets/-1928340783_3375",
      "/assets/-1871562056_4722",
      "/assets/1154117175_5888",
      "/assets/1896260709_9178",
      "/assets/-421841696_11837"
    ],
    "rankCSS": {
      "background-image": "url(assets/-1871562056_4722)",
      "background-size": "20px",
      "background-color": "transparent",
      "top": "5px",
      "left": "75px",
      "width": "20px",
      "height": "32.031872508px",
      "border-radius": "0px",
      "color": "transparent"
    },
    "leaveRoutine": [
      {
        "func": "CALL",
        "routine": "enterRoutine"
      }
    ],
    "enterRoutine": [
      {
        "func": "GET",
        "property": "task",
        "variable": "task",
        "collection": [
          "${PROPERTY parent}"
        ]
      },
      {
        "func": "IF",
        "operand1": "${task}",
        "operand2": "rankPile",
        "thenRoutine": [
          {
            "func": "COUNT",
            "holder": "${thisID}"
          },
          "var images = ${PROPERTY images}",
          "var image = ${images.$COUNT}",
          "var rankCSS = ${PROPERTY rankCSS}",
          "var BG = 'url(' + ${image}",
          "var BG = ${BG} + ')'",
          "var rankCSS.background-image = ${BG}",
          {
            "func": "SET",
            "property": "handleCSS",
            "value": "${rankCSS}",
            "collection": "thisButton"
          }
        ],
        "elseRoutine": [
          {
            "func": "SET",
            "property": "handleCSS",
            "value": null,
            "collection": "thisButton"
          }
        ]
      }
    ],
    "id": "25e2",
    "handleCSS": {
      "background-image": "url(/assets/-421841696_11837)",
      "background-size": "20px",
      "background-color": "transparent",
      "top": "5px",
      "left": "75px",
      "width": "20px",
      "height": "32.031872508px",
      "border-radius": "0px",
      "color": "transparent"
    },
    "z": 10115,
    "parent": "mxep1"
  },
  "pbo0": {
    "deck": "mxepD1",
    "type": "card",
    "cardType": "C 04",
    "id": "pbo0",
    "z": 10114,
    "parent": "25e2",
    "activeFace": 1
  }
}